{
    "products": [
 {
    "id": 1,
    "productType": "hoodie",
    "color": 1,
    "img": "/src/assets/hoodie-orange.png",
    "productTarget": "women",
    "onSale": true,
    "price": 149
},
{
    "id": 2,
    "productType": "tshirt",
    "color": 2,
    "img": "/src/assets/tshirt-purple.png",
    "productTarget": "kids",
    "onSale": false,
    "price": 99
}, {
    "id": 3,
    "productType": "hoodie",
    "color": 3,
    "img": "/src/assets/hoodie-white.png",
    "productTarget": "men",
    "onSale": true,
    "price": 99
}, {
    "id": 4,
    "productType": "tshirt",
    "color": 2,
    "img": "/src/assets/tshirt-purple.png",
    "productTarget": "men",
    "onSale": true,
    "price": 299
}, {
    "id": 5,
    "productType": "assec",
    "color": 3,
    "img": "/src/assets/assec-white.png",
    "productTarget": "kids",
    "onSale": true,
    "price": 199
}, {
    "id": 6,
    "productType": "tshirt",
    "color": 1,
    "img": "/src/assets/tshirt-orange.png",
    "productTarget": "kids",
    "onSale": true,
    "price": 199
}, {
    "id": 7,
    "productType": "hoodie",
    "color": 3,
    "img": "/src/assets/hoodie-white.png",
    "productTarget": "women",
    "onSale": true,
    "price": 149
}, {
    "id": 8,
    "productType": "assec",
    "color": 1,
    "img": "/src/assets/assec-orange.png",
    "productTarget": "men",
    "onSale": true,
    "price": 299
}, {
    "id": 9,
    "productType": "tshirt",
    "color": 3,
    "img": "/src/assets/tshirt-white.png",
    "productTarget": "men",
    "onSale": true,
    "price": 149
}, {
    "id": 10,
    "productType": "hoodie",
    "color": 2,
    "img": "/src/assets/hoodie-purple.png",
    "productTarget": "kids",
    "onSale": true,
    "price": 99
}, {
    "id": 11,
    "productType": "tshirt",
    "color": 1,
    "img": "/src/assets/tshirt-orange.png",
    "productTarget": "kids",
    "onSale": false,
    "price": 299
}, {
    "id": 12,
    "productType": "hoodie",
    "color": 3,
    "img": "/src/assets/hoodie-white.png",
    "productTarget": "kids",
    "onSale": true,
    "price": 99
}, {
    "id": 13,
    "productType": "hoodie",
    "color": 1,
    "img": "/src/assets/hoodie-orange.png",
    "productTarget": "women",
    "onSale": false,
    "price": 99
}, {
    "id": 14,
    "productType": "trousers",
    "color": 1,
    "img": "/src/assets/trousers-orange.png",
    "productTarget": "men",
    "onSale": true,
    "price": 199
}, {
    "id": 15,
    "productType": "hoodie",
    "color": 1,
    "img": "/src/assets/hoodie-orange.png",
    "productTarget": "women",
    "onSale": false,
    "price": 99
}, {
    "id": 16,
    "productType": "assec",
    "color": 2,
    "img": "/src/assets/assec-purple.png",
    "productTarget": "women",
    "onSale": true,
    "price": 299
}, {
    "id": 17,
    "productType": "tshirt",
    "color": 1,
    "img": "/src/assets/tshirt-orange.png",
    "productTarget": "men",
    "onSale": true,
    "price": 299
}, {
    "id": 18,
    "productType": "hoodie",
    "color": 2,
    "img": "/src/assets/hoodie-purple.png",
    "productTarget": "men",
    "onSale": true,
    "price": 299
}, {
    "id": 19,
    "productType": "trousers",
    "color": 1,
    "img": "/src/assets/trousers-orange.png",
    "productTarget": "women",
    "onSale": false,
    "price": 199
}, {
    "id": 20,
    "productType": "assec",
    "color": 2,
    "img": "/src/assets/assec-purple.png",
    "productTarget": "men",
    "onSale": true,
    "price": 199
}, {
    "id": 21,
    "productType": "assec",
    "color": 1,
    "img": "/src/assets/assec-orange.png",
    "productTarget": "women",
    "onSale": false,
    "price": 149
}, {
    "id": 22,
    "productType": "assec",
    "color": 2,
    "img": "/src/assets/assec-purple.png",
    "productTarget": "men",
    "onSale": true,
    "price": 99
}, {
    "id": 23,
    "productType": "trousers",
    "color": 3,
    "img": "/src/assets/trousers-blue.png",
    "productTarget": "women",
    "onSale": true,
    "price": 149
}, {
    "id": 24,
    "productType": "tshirt",
    "color": 2,
    "img": "/src/assets/tshirt-purple.png",
    "productTarget": "women",
    "onSale": true,
    "price": 99
}, {
    "id": 25,
    "productType": "assec",
    "color": 3,
    "img": "/src/assets/assec-white.png",
    "productTarget": "women",
    "onSale": true,
    "price": 149
}, {
    "id": 26,
    "productType": "trousers",
    "color": 1,
    "img": "/src/assets/trousers-orange.png",
    "productTarget": "women",
    "onSale": true,
    "price": 99
}, {
    "id": 27,
    "productType": "tshirt",
    "color": 2,
    "img": "/src/assets/tshirt-purple.png",
    "productTarget": "men",
    "onSale": false,
    "price": 99
}, {
    "id": 28,
    "productType": "tshirt",
    "color": 3,
    "img": "/src/assets/tshirt-white.png",
    "productTarget": "kids",
    "onSale": false,
    "price": 99
}, {
    "id": 29,
    "productType": "trousers",
    "color": 2,
    "img": "/src/assets/trousers-purple.png",
    "productTarget": "women",
    "onSale": false,
    "price": 299
}, {
    "id": 30,
    "productType": "assec",
    "color": 1,
    "img": "/src/assets/assec-orange.png",
    "productTarget": "men",
    "onSale": true,
    "price": 299
}, {
    "id": 31,
    "productType": "trousers",
    "color": 1,
    "img": "/src/assets/trousers-orange.png",
    "productTarget": "men",
    "onSale": true,
    "price": 299
}, {
    "id": 32,
    "productType": "trousers",
    "color": 1,
    "img": "/src/assets/trousers-orange.png",
    "productTarget": "kids",
    "onSale": true,
    "price": 299
}, {
    "id": 33,
    "productType": "hoodie",
    "color": 3,
    "img": "/src/assets/hoodie-white.png",
    "productTarget": "kids",
    "onSale": false,
    "price": 99
}, {
    "id": 34,
    "productType": "trousers",
    "color": 2,
    "img": "/src/assets/trousers-purple.png",
    "productTarget": "women",
    "onSale": true,
    "price": 199
}, {
    "id": 35,
    "productType": "tshirt",
    "color": 3,
    "img": "/src/assets/tshirt-white.png",
    "productTarget": "men",
    "onSale": true,
    "price": 99
}, {
    "id": 36,
    "productType": "hoodie",
    "color": 3,
    "img": "/src/assets/hoodie-white.png",
    "productTarget": "men",
    "onSale": false,
    "price": 299
}, {
    "id": 37,
    "productType": "trousers",
    "color": 2,
    "img": "/src/assets/trousers-purple.png",
    "productTarget": "women",
    "onSale": true,
    "price": 99
}, {
    "id": 38,
    "productType": "assec",
    "color": 2,
    "img": "/src/assets/assec-purple.png",
    "productTarget": "women",
    "onSale": false,
    "price": 199
}, {
    "id": 39,
    "productType": "trousers",
    "color": 2,
    "img": "/src/assets/trousers-purple.png",
    "productTarget": "men",
    "onSale": true,
    "price": 149
}, {
    "id": 40,
    "productType": "hoodie",
    "color": 2,
    "img": "/src/assets/hoodie-purple.png",
    "productTarget": "kids",
    "onSale": false,
    "price": 199
}, {
    "id": 41,
    "productType": "tshirt",
    "color": 3,
    "img": "/src/assets/tshirt-white.png",
    "productTarget": "men",
    "onSale": false,
    "price": 99
}, {
    "id": 42,
    "productType": "hoodie",
    "color": 2,
    "img": "/src/assets/hoodie-purple.png",
    "productTarget": "men",
    "onSale": false,
    "price": 299
}, {
    "id": 43,
    "productType": "hoodie",
    "color": 1,
    "img": "/src/assets/hoodie-orange.png",
    "productTarget": "kids",
    "onSale": false,
    "price": 149
}, {
    "id": 44,
    "productType": "assec",
    "color": 2,
    "img": "/src/assets/assec-purple.png",
    "productTarget": "women",
    "onSale": true,
    "price": 299
}, {
    "id": 45,
    "productType": "tshirt",
    "color": 2,
    "img": "/src/assets/tshirt-purple.png",
    "productTarget": "women",
    "onSale": true,
    "price": 199
}, {
    "id": 46,
    "productType": "tshirt",
    "color": 3,
    "img": "/src/assets/tshirt-white.png",
    "productTarget": "women",
    "onSale": true,
    "price": 149
}, {
    "id": 47,
    "productType": "hoodie",
    "color": 2,
    "img": "/src/assets/hoodie-purple.png",
    "productTarget": "kids",
    "onSale": false,
    "price": 199
}, {
    "id": 48,
    "productType": "assec",
    "color": 2,
    "img": "/src/assets/assec-purple.png",
    "productTarget": "women",
    "onSale": true,
    "price": 99
}, {
    "id": 49,
    "productType": "tshirt",
    "color": 2,
    "img": "/src/assets/tshirt-purple.png",
    "productTarget": "men",
    "onSale": true,
    "price": 99
}, {
    "id": 50,
    "productType": "hoodie",
    "color": 2,
    "img": "/src/assets/hoodie-purple.png",
    "productTarget": "kids",
    "onSale": true,
    "price": 99
}
]

}